CHANGES.txt
README.txt
ez_setup.py
setup.py
src/curry/__init__.py
src/curry/astgae.py
src/curry/astutils.py
src/curry/codegen.py
src/curry.egg-info/PKG-INFO
src/curry.egg-info/SOURCES.txt
src/curry.egg-info/dependency_links.txt
src/curry.egg-info/not-zip-safe
src/curry.egg-info/top_level.txt
src/curry/tests/__init__.py
src/curry/tests/base.py
src/curry/tests/examples.py