Metadata-Version: 1.0
Name: curry
Version: 0.2
Summary: Partial application of Python methods.
Home-page: UNKNOWN
Author: Malthe Borch
Author-email: mborch@gmail.com
License: BSD
Keywords: cooking partial curry optimization ast pickle
Platform: UNKNOWN
Classifier: Development Status :: 3 - Alpha
Classifier: Intended Audience :: Developers
Classifier: Programming Language :: Python
